<?xml version="1.0" encoding="UTF-8"?>
<!DOCTYPE suite SYSTEM "http://testng.org/testng-1.0.dtd">
<suite name="SFLY3">

    <groups>
        <run>
            <include name="Regression"/>
        </run>
    </groups>

    <test verbose="2" preserve-order="true" name="Regression Testing">
        <parameter name="browser" value="CHROME"></parameter>
        <classes>
            <class name="com.sfly3.scripts.TC_002_MOGifts"></class>
            <class name="com.sfly3.scripts.TC_001_LoginSfly3"></class>

        </classes>
    </test>
</suite>